{
  "name": "myexample133",
  "icon": "calendar",
  "order": 166,
  "title": "InlinePickList basic",
  "navigation": {
    "menu": [
      {
        "title": "List",
        "child": [
          {
            "viewName": "myexample133list"
          }
        ]
      },
      {
        "title": "Info",
        "child": [
          {
            "viewName": "myexample133info"
          }
        ]
      },
      {
        "title": "Form",
        "child": [
          {
            "viewName": "myexample133form"
          }
        ]
      }
    ]
  }
}