{
  "name": "myexample163",
  "icon": "calendar",
  "order": 11,
  "title": "Input validation field level dynamic",
  "navigation": {
    "menu": [
      {
        "title": "List",
        "child": [
          {
            "viewName": "myexample163list"
          }
        ]
      },
      {
        "title": "Info",
        "child": [
          {
            "viewName": "myexample163info"
          }
        ]
      },
      {
        "title": "Form",
        "child": [
          {
            "viewName": "myexample163form"
          }
        ]
      }
    ]
  }
}