{
  "name": "myexample5",
  "icon": "calendar",
  "order": 703,
  "title": "Percent drilldown",
  "navigation": {
    "menu": [
      {
        "title": "List",
        "child": [
          {
            "viewName": "myexample5list"
          }
        ]
      },
      {
        "title": "Info",
        "child": [
          {
            "viewName": "myexample5info"
          }
        ]
      },
      {
        "title": "Form",
        "child": [
          {
            "viewName": "myexample5form"
          }
        ]
      }
    ]
  }
}