{
  "name": "myexample2000info",
  "title": "My Example2000 Info",
  "template": "DashboardView",
  "url": "/screen/myexample2000/view/myexample2000info",
  "widgets": [
    {
      "widgetName": "myEntity2001AssocListPopup",
      "position": 20,
      "gridWidth": 24
    },
    {
      "widgetName": "SecondLevelMenu",
      "position": 0,
      "gridWidth": 24
    },
    {
      "widgetName": "MyExample2000Info",
      "position": 20,
      "gridWidth": 12
    }
  ],
  "rolesAllowed": [
    "CXBOX_USER"
  ]
}