{
  "name": "myexample292",
  "icon": "calendar",
  "order": 80,
  "title": "Percent field level validation dynamic",
  "navigation": {
    "menu": [
      {
        "title": "List",
        "child": [
          {
            "viewName": "myexample292list"
          }
        ]
      },
      {
        "title": "Info",
        "child": [
          {
            "viewName": "myexample292info"
          }
        ]
      },
      {
        "title": "Form",
        "child": [
          {
            "viewName": "myexample292form"
          }
        ]
      }
    ]
  }
}