{
  "name": "myexample4228",
  "icon": "calendar",
  "order": 42280,
  "title": "StatsBlock gridWidth",
  "navigation": {
    "menu": [
      {
        "title": "StatsBlock gridWidth=24",
        "child": [
          {
            "viewName": "MyExample4228Stat"
          }
        ]
      },
      {
        "title": "StatsBlock gridWidth=12",
        "child": [
          {
            "viewName": "MyExample4228Stat12"
          }
        ]
      },
      {
        "title": "StatsBlock gridWidth=6",
        "child": [
          {
            "viewName": "MyExample4228Stat6"
          }
        ]
      }
    ]
  }
}
