{
  "name": "MyExample3077ChildForm",
  "title": "",
  "type": "Form",
  "bc": "myexample3077",
  "fields": [
    {
      "label": "customField",
      "key": "customField",
      "type": "input"
    }
  ],
  "options": {
  "actionGroups": {
    "include": [
      "customSave",
      "cancel-create"
    ]
  },
    "layout": {
      "rows": [
        {
          "cols": [
            {
              "fieldKey": "customField",
              "span": 12
            }
          ]
        }
      ]
    }
  }
}
