{
  "name": "myexample152",
  "icon": "calendar",
  "order": 812,
  "title": "InlinePickList validation confirm",
  "navigation": {
    "type": "standard",
    "menu": [
      {
        "title": "List",
        "child": [
          {
            "viewName": "myexample152list"
          }
        ]
      },
      {
        "title": "Info",
        "child": [
          {
            "viewName": "myexample152info"
          }
        ]
      },
      {
        "title": "Form",
        "child": [
          {
            "viewName": "myexample152form"
          }
        ]
      }
    ]
  }
}