{
  "name": "myexample6101",
  "icon": "calendar",
  "order": 6101,
  "title": "Bulk upload",
  "navigation": {
    "type": "standard",
    "menu": [
      {
        "title": "with Confirm operation",
        "child": [
          {
            "viewName": "myexample6101list",
            "hidden": false
          },
          {
            "viewName": "myexample6101gh",
            "hidden": false
          },
          {
            "viewName": "myexample6101listtitle",
            "hidden": false
          },
          {
            "viewName": "myexample6101listwithouttitle",
            "hidden": false
          }
        ]
      },
      {
        "title": "without Confirm operation",
        "child": [
          {
            "viewName": "myexample6101checkboxtruelist"
          }
        ]
      }
    ]
  }
}