{
  "name": "myexample3202gh",
  "title": "MyExample3202",
  "template": "DashboardView",
  "url": "/screen/myexample3121/view/myexample3202gh",
  "widgets": [
    {
      "widgetName": "SecondLevelMenu",
      "position": 0,
      "gridWidth": 24
    },
    {
      "widgetName": "myEntity3202PickPick0PickListPopup",
      "position": 10,
      "gridWidth": 24
    },
    {
      "widgetName": "myEntity3202PickPickPickListPopup",
      "position": 20,
      "gridWidth": 24
    },
    {
      "widgetName": "myEntity3202MultiPickAssocListPopup",
      "position": 30,
      "gridWidth": 24
    },
    {
      "widgetName": "MyExample3202GHInput",
      "position": 40,
      "gridWidth": 24
    },
    {
      "widgetName": "MyExample3202GHText",
      "position": 50,
      "gridWidth": 24
    },
    {
      "widgetName": "MyExample3202GHDateTime",
      "position": 60,
      "gridWidth": 24
    },
    {
      "widgetName": "MyExample3202GHCheckBox",
      "position": 70,
      "gridWidth": 24
    },
    {
      "widgetName": "MyExample3202GHDate",
      "position": 80,
      "gridWidth": 24
    },
    {
      "widgetName": "MyExample3202GHDateTimeWithSeconds",
      "position": 90,
      "gridWidth": 24
    },
    {
      "widgetName": "MyExample3202GHFileUpload",
      "position": 100,
      "gridWidth": 24
    },
    {
      "widgetName": "MyExample3202GHDictionary",
      "position": 110,
      "gridWidth": 24
    },
    {
      "widgetName": "MyExample3202GHNumber",
      "position": 120,
      "gridWidth": 24
    },
    {
      "widgetName": "MyExample3202GH",
      "position": 130,
      "gridWidth": 24
    },
    {
      "widgetName": "MyExample3202GHPercent",
      "position": 140,
      "gridWidth": 24
    },
    {
      "widgetName": "MyExample3202GHMoney",
      "position": 150,
      "gridWidth": 24
    },
    {
      "widgetName": "MyExample3202GHRadio",
      "position": 160,
      "gridWidth": 24
    },
    {
      "widgetName": "MyExample3202GHInline",
      "position": 170,
      "gridWidth": 24
    },
    {
      "widgetName": "MyExample3202GHPicklist",
      "position": 180,
      "gridWidth": 24
    },
    {
      "widgetName": "MyExample3202GHMultifield",
      "position": 190,
      "gridWidth": 24
    },
    {
      "widgetName": "MyExample3202GHMultiSelect",
      "position": 200,
      "gridWidth": 24
    },
    {
      "widgetName": "MyExample3202GHHover",
      "position": 210,
      "gridWidth": 24
    },
    {
      "widgetName": "MyExample3202GHHint",
      "position": 220,
      "gridWidth": 24
    },
    {
      "widgetName": "MyExample3202GHMultivalue",
      "position": 230,
      "gridWidth": 24
    },
    {
      "widgetName": "MyExample3202GHHidden",
      "position": 240,
      "gridWidth": 24
    }
  ],
  "rolesAllowed": [
    "CXBOX_USER"
  ]
}
