{
  "name": "InputValidationRuntimeException",
  "icon": "calendar",
  "order": 12,
  "title": "Input validation runtime exception",
  "navigation": {
    "menu": [
      {
        "title": "List",
        "child": [
          {
            "viewName": "InputValidationRuntimeExceptionlist"
          }
        ]
      },
      {
        "title": "Info",
        "child": [
          {
            "viewName": "InputValidationRuntimeExceptioninfo"
          }
        ]
      },
      {
        "title": "Form",
        "child": [
          {
            "viewName": "InputValidationRuntimeExceptionform"
          }
        ]
      }
    ]
  }
}