{
  "name": "MyExample3616ListForAssoc",
  "title": "AssocListPopup widget",
  "type": "Form",
  "bc": "myexample3616",
  "fields": [
    {
      "label": "Custom Field Multivalue",
      "key": "customFieldMultivalue",
      "type": "multivalue",
      "displayedKey": "customFieldMultivalueDisplayedKey",
      "popupBcName": "myEntity3623Pick",
      "assocValueKey": "customField"
    }
  ],
  "options": {
    "actionGroups": {
      "include": []
    },
    "layout": {
      "rows": [
        {
          "cols": [
            {
              "fieldKey": "customFieldMultivalue",
              "span": 12
            }
          ]
        }
      ]
    }
  }
}

