{
  "name": "myexample293",
  "icon": "calendar",
  "order": 2013,
  "title": "Dictionary enum validation field level annotation",
  "navigation": {
    "type": "standard",
    "menu": [
      {
        "title": "List",
        "child": [
          {
            "viewName": "myexample293list"
          }
        ]
      },
      {
        "title": "Info",
        "child": [
          {
            "viewName": "myexample293info"
          }
        ]
      },
      {
        "title": "Form",
        "child": [
          {
            "viewName": "myexample293form"
          }
        ]
      }
    ]
  }
}